acall/__init__.py
acall/_modidx.py
acall/core.py
acall-0.0.2.dist-info/LICENSE
acall-0.0.2.dist-info/METADATA
acall-0.0.2.dist-info/WHEEL
acall-0.0.2.dist-info/entry_points.txt
acall-0.0.2.dist-info/top_level.txt
acall-0.0.2.dist-info/RECORD
