Metadata-Version: 2.1
Name: acall
Version: 0.0.2
Summary: acall
Home-page: https://github.com/dsm-72/acall
Author: dsm-72
Author-email: sumner.magruder@yale.edu
License: Apache Software License 2.0
Keywords: acall
Classifier: Development Status :: 4 - Beta
Classifier: Intended Audience :: Developers
Classifier: Natural Language :: English
Classifier: Programming Language :: Python :: 3.11
Classifier: License :: OSI Approved :: Apache Software License
Requires-Python: >=3.11
License-File: LICENSE
Requires-Dist: atyp
Requires-Dist: nchr
Requires-Dist: nlit
Requires-Dist: chck
Requires-Dist: idfunc
Requires-Dist: xpass
Provides-Extra: dev
